scripts/__init__.py
scripts/migrate/__init__.py
scripts/migrate/__main__.py
scripts/migrate/_migrate.py
scripts/migrate/_plugin_doc.py
scripts/migrate/_plugin_py3to2.py
scripts/migrate/test_migrate.py
ucloud/__init__.py
ucloud/_compat.py
ucloud/client.py
ucloud/version.py
ucloud/core/__init__.py
ucloud/core/auth/__init__.py
ucloud/core/auth/_cfg.py
ucloud/core/client/__init__.py
ucloud/core/client/_cfg.py
ucloud/core/client/_client.py
ucloud/core/exc/__init__.py
ucloud/core/exc/_exc.py
ucloud/core/transport/__init__.py
ucloud/core/transport/_requests.py
ucloud/core/transport/http.py
ucloud/core/transport/utils.py
ucloud/core/typesystem/__init__.py
ucloud/core/typesystem/abstract.py
ucloud/core/typesystem/encoder.py
ucloud/core/typesystem/fields.py
ucloud/core/typesystem/schema.py
ucloud/core/utils/__init__.py
ucloud/core/utils/compat.py
ucloud/core/utils/deco.py
ucloud/core/utils/log.py
ucloud/core/utils/middleware.py
ucloud/helpers/__init__.py
ucloud/helpers/utils.py
ucloud/helpers/wait.py
ucloud/services/__init__.py
ucloud/services/ipsecvpn/__init__.py
ucloud/services/ipsecvpn/client.py
ucloud/services/ipsecvpn/schemas/__init__.py
ucloud/services/ipsecvpn/schemas/apis.py
ucloud/services/ipsecvpn/schemas/models.py
ucloud/services/pathx/__init__.py
ucloud/services/pathx/client.py
ucloud/services/pathx/schemas/__init__.py
ucloud/services/pathx/schemas/apis.py
ucloud/services/pathx/schemas/models.py
ucloud/services/stepflow/__init__.py
ucloud/services/stepflow/client.py
ucloud/services/stepflow/schemas/__init__.py
ucloud/services/stepflow/schemas/apis.py
ucloud/services/stepflow/schemas/models.py
ucloud/services/uaccount/__init__.py
ucloud/services/uaccount/client.py
ucloud/services/uaccount/schemas/__init__.py
ucloud/services/uaccount/schemas/apis.py
ucloud/services/uaccount/schemas/models.py
ucloud/services/ucdn/__init__.py
ucloud/services/ucdn/client.py
ucloud/services/ucdn/schemas/__init__.py
ucloud/services/ucdn/schemas/apis.py
ucloud_sdk_python2-0.9.2.dist-info/LICENSE
ucloud_sdk_python2-0.9.2.dist-info/METADATA
ucloud_sdk_python2-0.9.2.dist-info/WHEEL
ucloud_sdk_python2-0.9.2.dist-info/top_level.txt
ucloud_sdk_python2-0.9.2.dist-info/RECORD
