Metadata-Version: 2.1
Name: ucloud-sdk-python2
Version: 0.9.2
Summary: UCloud Service Development Kit - Python
Home-page: https://github.com/ucloud/ucloud-sdk-python2
Author: ucloud
Author-email: esl_ipdd@ucloud.cn
License: Apache License 2.0
Platform: UNKNOWN
Classifier: Development Status :: 3 - Alpha
Classifier: Environment :: Console
Classifier: Environment :: Web Environment
Classifier: Intended Audience :: Developers
Classifier: Intended Audience :: System Administrators
Classifier: License :: OSI Approved :: Apache Software License
Classifier: Programming Language :: Python :: 2.7
Classifier: Programming Language :: Python :: 2 :: Only
Classifier: Topic :: Software Development
Requires-Python: >=2.7
Requires-Dist: requests
Provides-Extra: ci
Requires-Dist: sphinx ; extra == 'ci'
Requires-Dist: pytest ; extra == 'ci'
Requires-Dist: pytest-cov ; extra == 'ci'
Requires-Dist: requests ; extra == 'ci'
Requires-Dist: flake8 (>=3.6.0) ; extra == 'ci'
Provides-Extra: dev
Requires-Dist: sphinx ; extra == 'dev'
Requires-Dist: pytest-cov ; extra == 'dev'
Requires-Dist: pytest ; extra == 'dev'
Requires-Dist: black ; extra == 'dev'
Requires-Dist: requests ; extra == 'dev'
Requires-Dist: flake8 (>=3.6.0) ; extra == 'dev'
Provides-Extra: doc
Requires-Dist: requests ; extra == 'doc'
Requires-Dist: sphinx ; extra == 'doc'
Provides-Extra: test
Requires-Dist: requests ; extra == 'test'
Requires-Dist: flake8 (>=3.6.0) ; extra == 'test'
Requires-Dist: pytest ; extra == 'test'
Requires-Dist: pytest-cov ; extra == 'test'
